CHANGELOG.txt
LICENSE.txt
MANIFEST.in
README.md
requirements.txt
setup.py
Caribe/T5_Caribe.py
Caribe/__init__.py
Caribe/caribe_generate.py
Caribe.egg-info/PKG-INFO
Caribe.egg-info/SOURCES.txt
Caribe.egg-info/dependency_links.txt
Caribe.egg-info/requires.txt
Caribe.egg-info/top_level.txt
Caribe/guyanese/__init__.py