Metadata-Version: 2.1
Name: Caribe
Version: 0.9.2
Summary: Caribbean English Creoles to Standard English
Home-page: UNKNOWN
Author: Keston Smith
Author-email: keston.smith@my.uwi.edu
License: Apache License, Version 2.0
Keywords: Translator
Platform: UNKNOWN
Classifier: Development Status :: 5 - Production/Stable
Classifier: Intended Audience :: Education
Classifier: Operating System :: Microsoft :: Windows :: Windows 10
Classifier: License :: OSI Approved :: Apache Software License
Classifier: Programming Language :: Python :: 3
License-File: LICENSE.txt
